fastapi_keycloak_lzjxc/__init__.py
fastapi_keycloak_lzjxc/api.py
fastapi_keycloak_lzjxc/exceptions.py
fastapi_keycloak_lzjxc/model.py
fastapi_keycloak_lzjxc-0.1.0.dist-info/LICENSE
fastapi_keycloak_lzjxc-0.1.0.dist-info/METADATA
fastapi_keycloak_lzjxc-0.1.0.dist-info/WHEEL
fastapi_keycloak_lzjxc-0.1.0.dist-info/RECORD
